pytrends_support_hvk/__init__.py
pytrends_support_hvk/google_trends.py
pytrends_support_hvk-0.0.1.dist-info/METADATA
pytrends_support_hvk-0.0.1.dist-info/WHEEL
pytrends_support_hvk-0.0.1.dist-info/licenses/LICENSE.txt
pytrends_support_hvk-0.0.1.dist-info/RECORD
