Metadata-Version: 2.1
Name: pytrends_support_hvk
Version: 0.0.1
Summary: A small package that makes pytrends easier to use, creating a class for more easily selecting dates for queries
Project-URL: Homepage, https://github.com/pypa/sampleproject
Project-URL: Bug Tracker, https://github.com/pypa/sampleproject/issues
Author-email: Holly Krambeck <jeepney.survey@gmail.com>
License: Copyright (c) 2018 The Python Packaging Authority
Classifier: License :: OSI Approved :: MIT License
Classifier: Operating System :: OS Independent
Classifier: Programming Language :: Python :: 3
Requires-Python: >=3.7
